fastener/__init__.py
fastener/fastener.py
fastener/item.py
fastener/random_utils.py
fastener-1.0.4.dist-info/LICENSE
fastener-1.0.4.dist-info/METADATA
fastener-1.0.4.dist-info/WHEEL
fastener-1.0.4.dist-info/top_level.txt
fastener-1.0.4.dist-info/RECORD
