Metadata-Version: 2.1
Name: fastener
Version: 1.0.4
Summary: Feature selection enabled by entropy
Home-page: https://github.com/JozefStefanInstitute/FASTENER.git
Author: Filip Koprivec, Klemen Kenda, Gal Petkovsek
Author-email: 
License: MIT
Platform: UNKNOWN
Classifier: Programming Language :: Python :: 3.6
Classifier: License :: OSI Approved :: MIT License
Classifier: Operating System :: OS Independent
Classifier: Intended Audience :: Science/Research
Classifier: Natural Language :: English
Classifier: Topic :: Scientific/Engineering :: Artificial Intelligence
Requires-Python: >=3.6
Requires-Dist: mypy
Requires-Dist: scikit-learn
Provides-Extra: examples
Requires-Dist: pandas (==1.1.3) ; extra == 'examples'
